{"Code":"1","Total":"4","Msg":[{"product_id":"5e5c92d9-5be9-450d-b1e5-d269ceea184a","name":"起司咔啦雞腿排熱壓吐司 ","price":100,"supplier_account":"2024A56","img":"A56-02.png","remark":"1份, 葷食","place":"","stockList":[{"product_stock_id":"0576e576-b66b-11ee-90fa-000c299306d6","stock":100,"total":100,"start_time":"14:30","end_time":"15:00"},{"product_stock_id":"0576e74e-b66b-11ee-90fa-000c299306d6","stock":100,"total":100,"start_time":"13:30","end_time":"14:00"},{"product_stock_id":"0576e8f6-b66b-11ee-90fa-000c299306d6","stock":100,"total":100,"start_time":"15:30","end_time":"16:00"},{"product_stock_id":"0576eaa8-b66b-11ee-90fa-000c299306d6","stock":100,"total":100,"start_time":"16:30","end_time":"17:00"},{"product_stock_id":"0576ec41-b66b-11ee-90fa-000c299306d6","stock":100,"total":100,"start_time":"15:00","end_time":"15:30"},{"product_stock_id":"0576ede3-b66b-11ee-90fa-000c299306d6","stock":100,"total":100,"start_time":"16:00","end_time":"16:30"},{"product_stock_id":"0576ef76-b66b-11ee-90fa-000c299306d6","stock":100,"total":100,"start_time":"14:00","end_time":"14:30"},{"product_stock_id":"05771429-b66b-11ee-90fa-000c299306d6","stock":100,"total":100,"start_time":"13:00","end_time":"13:30"},{"product_stock_id":"05771723-b66b-11ee-90fa-000c299306d6","stock":100,"total":100,"start_time":"12:30","end_time":"13:00"},{"product_stock_id":"0577191f-b66b-11ee-90fa-000c299306d6","stock":100,"total":100,"start_time":"12:00","end_time":"12:30"}]},{"product_id":"7b6bc076-a196-4e90-888a-35e1d0a0f509","name":"手工花生糖(口味:原味/海苔/芝麻)","price":220,"supplier_account":"2024A56","img":"A56-04.png","remark":"450g, 全素","place":"","stockList":[{"product_stock_id":"05771b10-b66b-11ee-90fa-000c299306d6","stock":20,"total":20,"start_time":"14:30","end_time":"15:00"},{"product_stock_id":"05771cb4-b66b-11ee-90fa-000c299306d6","stock":20,"total":20,"start_time":"13:30","end_time":"14:00"},{"product_stock_id":"05771e45-b66b-11ee-90fa-000c299306d6","stock":20,"total":20,"start_time":"15:30","end_time":"16:00"},{"product_stock_id":"05771fe1-b66b-11ee-90fa-000c299306d6","stock":20,"total":20,"start_time":"16:30","end_time":"17:00"},{"product_stock_id":"0577217a-b66b-11ee-90fa-000c299306d6","stock":20,"total":20,"start_time":"15:00","end_time":"15:30"},{"product_stock_id":"05772327-b66b-11ee-90fa-000c299306d6","stock":20,"total":20,"start_time":"16:00","end_time":"16:30"},{"product_stock_id":"057724a6-b66b-11ee-90fa-000c299306d6","stock":20,"total":20,"start_time":"14:00","end_time":"14:30"},{"product_stock_id":"05772635-b66b-11ee-90fa-000c299306d6","stock":20,"total":20,"start_time":"13:00","end_time":"13:30"},{"product_stock_id":"057727c6-b66b-11ee-90fa-000c299306d6","stock":20,"total":20,"start_time":"12:30","end_time":"13:00"},{"product_stock_id":"05772949-b66b-11ee-90fa-000c299306d6","stock":20,"total":20,"start_time":"12:00","end_time":"12:30"}]},{"product_id":"8f73a8dc-dc22-4101-a30f-252064f7b374","name":"韓式泡菜牛肉熱壓吐司","price":100,"supplier_account":"2024A56","img":"A56-01.png","remark":"1份, 葷食","place":"","stockList":[{"product_stock_id":"05772ad7-b66b-11ee-90fa-000c299306d6","stock":30,"total":30,"start_time":"14:30","end_time":"15:00"},{"product_stock_id":"05772c6b-b66b-11ee-90fa-000c299306d6","stock":30,"total":30,"start_time":"13:30","end_time":"14:00"},{"product_stock_id":"05772dfa-b66b-11ee-90fa-000c299306d6","stock":30,"total":30,"start_time":"15:30","end_time":"16:00"},{"product_stock_id":"05772f8c-b66b-11ee-90fa-000c299306d6","stock":30,"total":30,"start_time":"16:30","end_time":"17:00"},{"product_stock_id":"05773121-b66b-11ee-90fa-000c299306d6","stock":30,"total":30,"start_time":"15:00","end_time":"15:30"},{"product_stock_id":"057732e0-b66b-11ee-90fa-000c299306d6","stock":30,"total":30,"start_time":"16:00","end_time":"16:30"},{"product_stock_id":"05773470-b66b-11ee-90fa-000c299306d6","stock":30,"total":30,"start_time":"14:00","end_time":"14:30"},{"product_stock_id":"057735f4-b66b-11ee-90fa-000c299306d6","stock":30,"total":30,"start_time":"13:00","end_time":"13:30"},{"product_stock_id":"0577377b-b66b-11ee-90fa-000c299306d6","stock":30,"total":30,"start_time":"12:30","end_time":"13:00"},{"product_stock_id":"05773901-b66b-11ee-90fa-000c299306d6","stock":30,"total":30,"start_time":"12:00","end_time":"12:30"}]},{"product_id":"c6878914-a20a-4ae9-b54c-6a8685f2b386","name":"蔓越莓雪Q餅","price":100,"supplier_account":"2024A56","img":"A56-03.png","remark":"120g, 葷食","place":"","stockList":[{"product_stock_id":"05773a83-b66b-11ee-90fa-000c299306d6","stock":100,"total":100,"start_time":"14:30","end_time":"15:00"},{"product_stock_id":"05773c19-b66b-11ee-90fa-000c299306d6","stock":100,"total":100,"start_time":"13:30","end_time":"14:00"},{"product_stock_id":"05773d9f-b66b-11ee-90fa-000c299306d6","stock":100,"total":100,"start_time":"15:30","end_time":"16:00"},{"product_stock_id":"05773f42-b66b-11ee-90fa-000c299306d6","stock":100,"total":100,"start_time":"16:30","end_time":"17:00"},{"product_stock_id":"057740eb-b66b-11ee-90fa-000c299306d6","stock":100,"total":100,"start_time":"15:00","end_time":"15:30"},{"product_stock_id":"05774296-b66b-11ee-90fa-000c299306d6","stock":100,"total":100,"start_time":"16:00","end_time":"16:30"},{"product_stock_id":"05777ce3-b66b-11ee-90fa-000c299306d6","stock":100,"total":100,"start_time":"14:00","end_time":"14:30"},{"product_stock_id":"05778072-b66b-11ee-90fa-000c299306d6","stock":100,"total":100,"start_time":"13:00","end_time":"13:30"},{"product_stock_id":"05778223-b66b-11ee-90fa-000c299306d6","stock":100,"total":100,"start_time":"12:30","end_time":"13:00"},{"product_stock_id":"057783b5-b66b-11ee-90fa-000c299306d6","stock":100,"total":100,"start_time":"12:00","end_time":"12:30"}]}],"ExtraInfo":""}